{
    "id" : 1,
    "name" : "person 1",
    "mood" : 0.4,
    "rooms" : [
        {
            "id" : 1,
            "name" : "room 1",
            "mood" : -0.4
        },
        {
            "id" : 2,
            "name" : "room 2",
            "mood" : -0.3
        },
        {
            "id" : 3,
            "name" : "room 3",
            "mood" : -0.2
        },
        {
            "id" : 4,
            "name" : "room 4",
            "mood" : 0.8
        },
        {
            "id" : 5,
            "name" : "room 5",
            "mood" : 0.7
        },
        {
            "id" : 6,
            "name" : "room 6",
            "mood" : -0.2
        },
        {
            "id" : 7,
            "name" : "room 7",
            "mood" : -0.8
        },
        {
            "id" : 8,
            "name" : "room 8",
            "mood" : -0.42
        }
    ]
}
